{
  "id": "FRP",
  "product_id": "FRP",
  "name": "FRP – HYBRID POLYMER ROLLABLE FRP ADHESIVE",
  "full_name": "FRP – HYBRID POLYMER ROLLABLE FRP ADHESIVE",
  "description": "ForzaBOND™ FRP Modified Silane Rollable Flooring Adhesive",
  "brand": "forza_bond",
  "category": "BOND",
  "industry": "construction_industry",
  "chemistry": "MS",
  "url": "https://forzabuilt.com/product/frp/",
  "image": "https://forzabuilt.com/wp-content/uploads/2023/12/FRP-Rollable-Adhesive-v2.png",
  "images": [
    "https://forzabuilt.com/wp-content/uploads/2023/12/FRP-Rollable-Adhesive-v2.png"
  ],
  "applications": [
    "The FRP modified silane rollable flooring adhesive is a high-performance adhesive that is specifically designed to bond a variety of substrates, including metal flooring, plywood, and vinyls.",
    "This adhesive is ideal for use in refrigerated and walk-in coolers, as it is able to withstand the extreme temperatures and conditions found in these environments."
  ],
  "benefits": [
    "Excellent bonding properties to a variety of substrates, including metal flooring, plywood, and vinyls",
    "Can be used in refrigerated and walk-in coolers",
    "Can withstand extreme temperatures and conditions",
    "High solids content for excellent coverage and reduced shrinkage",
    "Easy to apply and rollable",
    "Tack-free time of 2-4 hours",
    "Short cure time of 24-48 hours",
    "High shear and peel strength for maximum durability"
  ],
  "howToUse": [
    "Clean the substrate thoroughly, removing any dirt, debris, or contaminants.",
    "Apply the adhesive using a trowel or roller, ensuring an even and consistent coverage.",
    "Allow the adhesive to dry for 2-4 hours, or until it is tack-free.",
    "Lay the flooring material into the adhesive, pressing down firmly to ensure a secure bond.",
    "Allow the adhesive to cure for 24-48 hours before exposing it to foot traffic or heavy use."
  ],
  "sizing": [
    "28 oz",
    "20 oz",
    "5 Gallon",
    "55 Gallon"
  ],
  "technical": [],
  "scrapedAt": "2025-10-24T17:02:47.255Z",
  "published": false,
  "notes": "Scraped from WordPress Elementor site - needs review and technical data"
}